LICENSE
MANIFEST.in
README.md
setup.cfg
setup.py
wc_delivery_auto/__init__.py
wc_delivery_auto/const.py
wc_delivery_auto/exceptions.py
wc_delivery_auto/query.py
wc_delivery_auto/client/__init__.py
wc_delivery_auto/client/client.py
wc_delivery_auto/client/geography.py
wc_delivery_auto/client/utils.py
wc_delivery_auto_sdk.egg-info/PKG-INFO
wc_delivery_auto_sdk.egg-info/SOURCES.txt
wc_delivery_auto_sdk.egg-info/dependency_links.txt
wc_delivery_auto_sdk.egg-info/requires.txt
wc_delivery_auto_sdk.egg-info/top_level.txt